gh_tools/__init__.py
gh_tools/callbacks/__init__.py
gh_tools/callbacks/generate_images.py
gh_tools/callbacks/keras_storage.py
gh_tools/callbacks/log_code.py
gh_tools/callbacks/start_tensorboard.py
gh_tools/layers/__init__.py
gh_tools/layers/edit.py
gh_tools/layers/gradcam.py
gh_tools/layers/norms.py
gh_tools/models/WGAN_GP.py
gh_tools/models/__init__.py
gh_tools/utils/__init__.py
gh_tools/utils/colab.py
gh_tools/utils/helpers.py
gh_tools/utils/image.py
gh_tools/utils/version_service.py
gh_tools_gradient-0.0.7.dist-info/METADATA
gh_tools_gradient-0.0.7.dist-info/WHEEL
gh_tools_gradient-0.0.7.dist-info/top_level.txt
gh_tools_gradient-0.0.7.dist-info/RECORD
