Metadata-Version: 2.1
Name: gh-tools-gradient
Version: 0.0.7
Summary: Gradient Health training tools
Home-page: https://github.com/gradienthealth/gh-tools
Author: Ouwen Huang
Author-email: ouwen.huang@duke.edu
License: UNKNOWN
Platform: UNKNOWN
Classifier: Programming Language :: Python :: 3
Classifier: License :: OSI Approved :: MIT License
Classifier: Operating System :: OS Independent
Requires-Python: >=3.6
Requires-Dist: parse (>=1.19.0)
Requires-Dist: ipython
Requires-Dist: awscli (>=1.18.223)
Requires-Dist: tensorflow (>=2.4.1)
Requires-Dist: tfa-nightly
